MustafaInstagram/__init__.py
MustafaInstagram-0.0.1.dist-info/METADATA
MustafaInstagram-0.0.1.dist-info/WHEEL
MustafaInstagram-0.0.1.dist-info/top_level.txt
MustafaInstagram-0.0.1.dist-info/RECORD
