Metadata-Version: 2.1
Name: MustafaInstagram
Version: 0.0.1
Summary: A library to generate Instagram usernames.
Home-page: https://github.com/pypa/sampleproject
Author: Manus
Author-email: manus@example.com
License: UNKNOWN
Platform: UNKNOWN
Classifier: Programming Language :: Python :: 3
Classifier: License :: OSI Approved :: MIT License
Classifier: Operating System :: OS Independent
Requires-Python: >=3.6
Requires-Dist: requests
Requires-Dist: user-agent
